{
  "schemaVersion": 1,
  "task_id": "20260513-131242-16d127",
  "created_at": "2026-05-13T13:12:42.894Z",
  "updated_at": "2026-05-13T13:12:42.894Z",
  "kind": "ops",
  "status": "pending",
  "source": {
    "platform": "internal",
    "thread_id": null,
    "author": "master-md-refresh (intake)",
    "message_id": null
  },
  "input": {
    "text": "auto: refresh master.md for place_chijk2kjmcfmkwsrk9yzy9lxa-y (trigger=intake)",
    "attachments": []
  },
  "target": {
    "cli": "leads:build-master-md",
    "args": [
      "--entity-key",
      "place_chijk2kjmcfmkwsrk9yzy9lxa-y"
    ],
    "target_entity_key": null,
    "timeout_ms": 120000
  },
  "result": {
    "entity_keys": [],
    "exit_code": null,
    "duration_ms": null,
    "cost_usd": null
  },
  "progress": [],
  "error": null,
  "discord": {
    "thread_id": null,
    "status_message_id": null
  }
}
