{
  "requestedAt": "2026-05-07T23:17:02.862Z",
  "status": 200,
  "ok": true,
  "body": {
    "success": true,
    "clientSlug": "dark-shepherd-restaurant",
    "repo": "matthew6688/dark-shepherd-restaurant"
  },
  "payload": {
    "order_id": "fresh_dark_shepherd_dryrun_001",
    "email": "matthew6688@gmail.com",
    "client_slug": "dark-shepherd-restaurant",
    "repo": "matthew6688/dark-shepherd-restaurant",
    "preview_url": "https://dark-shepherd-restaurant-dev.pages.dev/",
    "task_path": "data/cases/dark-shepherd-restaurant/fresh_dark_shepherd_dryrun_001/publish-task.json"
  }
}
