{
  "schemaVersion": 1,
  "clientSlug": "the-vietnamese-restaurant-brisbane",
  "niche": "restaurant",
  "businessName": "The Vietnamese Restaurant",
  "createdAt": "2026-05-08T19:18:58.370Z",
  "updatedAt": "2026-05-08T19:18:58.370Z",
  "items": [
    {
      "key": "identity.name",
      "value": "The Vietnamese Restaurant",
      "sourceType": "manual",
      "sourceUrl": "https://discord.com/channels/1493925728570310756/1502385333155926027",
      "confidence": 0.86,
      "scrapedAt": "2026-05-08T19:18:58.370Z",
      "extractor": "discord_google_maps_discovery",
      "metadata": {
        "threadId": "1502385333155926027"
      }
    },
    {
      "key": "business.niche",
      "value": "restaurant",
      "sourceType": "manual",
      "sourceUrl": "https://discord.com/channels/1493925728570310756/1502385333155926027",
      "confidence": 0.82,
      "scrapedAt": "2026-05-08T19:18:58.370Z",
      "extractor": "discord_google_maps_discovery",
      "metadata": {
        "threadId": "1502385333155926027"
      }
    },
    {
      "key": "business.city",
      "value": "Fortitude Valley",
      "sourceType": "manual",
      "sourceUrl": "https://discord.com/channels/1493925728570310756/1502385333155926027",
      "confidence": 0.8,
      "scrapedAt": "2026-05-08T19:18:58.370Z",
      "extractor": "discord_google_maps_discovery",
      "metadata": {
        "threadId": "1502385333155926027"
      }
    },
    {
      "key": "contact.address",
      "value": "194 Wickham St, Fortitude Valley QLD 4006",
      "sourceType": "manual",
      "sourceUrl": "https://discord.com/channels/1493925728570310756/1502385333155926027",
      "confidence": 0.8,
      "scrapedAt": "2026-05-08T19:18:58.370Z",
      "extractor": "discord_google_maps_discovery",
      "metadata": {
        "threadId": "1502385333155926027"
      }
    },
    {
      "key": "contact.phone",
      "value": "0423 680 780",
      "sourceType": "manual",
      "sourceUrl": "https://discord.com/channels/1493925728570310756/1502385333155926027",
      "confidence": 0.82,
      "scrapedAt": "2026-05-08T19:18:58.370Z",
      "extractor": "discord_google_maps_discovery",
      "metadata": {
        "threadId": "1502385333155926027"
      }
    },
    {
      "key": "services.vietnamese_restaurant",
      "value": "Vietnamese restaurant",
      "sourceType": "manual",
      "sourceUrl": "https://discord.com/channels/1493925728570310756/1502385333155926027",
      "confidence": 0.72,
      "scrapedAt": "2026-05-08T19:18:58.370Z",
      "extractor": "discord_google_maps_discovery",
      "metadata": {
        "threadId": "1502385333155926027"
      }
    },
    {
      "key": "services.casual_dining",
      "value": "casual dining",
      "sourceType": "manual",
      "sourceUrl": "https://discord.com/channels/1493925728570310756/1502385333155926027",
      "confidence": 0.72,
      "scrapedAt": "2026-05-08T19:18:58.370Z",
      "extractor": "discord_google_maps_discovery",
      "metadata": {
        "threadId": "1502385333155926027"
      }
    },
    {
      "key": "services.takeaway",
      "value": "takeaway",
      "sourceType": "manual",
      "sourceUrl": "https://discord.com/channels/1493925728570310756/1502385333155926027",
      "confidence": 0.72,
      "scrapedAt": "2026-05-08T19:18:58.370Z",
      "extractor": "discord_google_maps_discovery",
      "metadata": {
        "threadId": "1502385333155926027"
      }
    },
    {
      "key": "opportunity.noDedicatedWebsiteFound",
      "value": "true",
      "sourceType": "manual",
      "sourceUrl": "https://discord.com/channels/1493925728570310756/1502385333155926027",
      "confidence": 0.72,
      "scrapedAt": "2026-05-08T19:18:58.370Z",
      "extractor": "discord_google_maps_discovery",
      "metadata": {
        "threadId": "1502385333155926027"
      }
    }
  ],
  "resolved": {
    "identity": {
      "name": {
        "value": "The Vietnamese Restaurant",
        "sourceType": "manual",
        "sourceUrl": "https://discord.com/channels/1493925728570310756/1502385333155926027",
        "confidence": 0.86,
        "scrapedAt": "2026-05-08T19:18:58.370Z",
        "extractor": "discord_google_maps_discovery"
      }
    },
    "business": {
      "niche": {
        "value": "restaurant",
        "sourceType": "manual",
        "sourceUrl": "https://discord.com/channels/1493925728570310756/1502385333155926027",
        "confidence": 0.82,
        "scrapedAt": "2026-05-08T19:18:58.370Z",
        "extractor": "discord_google_maps_discovery"
      },
      "city": {
        "value": "Fortitude Valley",
        "sourceType": "manual",
        "sourceUrl": "https://discord.com/channels/1493925728570310756/1502385333155926027",
        "confidence": 0.8,
        "scrapedAt": "2026-05-08T19:18:58.370Z",
        "extractor": "discord_google_maps_discovery"
      }
    },
    "contact": {
      "address": {
        "value": "194 Wickham St, Fortitude Valley QLD 4006",
        "sourceType": "manual",
        "sourceUrl": "https://discord.com/channels/1493925728570310756/1502385333155926027",
        "confidence": 0.8,
        "scrapedAt": "2026-05-08T19:18:58.370Z",
        "extractor": "discord_google_maps_discovery"
      },
      "phone": {
        "value": "0423 680 780",
        "sourceType": "manual",
        "sourceUrl": "https://discord.com/channels/1493925728570310756/1502385333155926027",
        "confidence": 0.82,
        "scrapedAt": "2026-05-08T19:18:58.370Z",
        "extractor": "discord_google_maps_discovery"
      }
    },
    "services": {
      "vietnamese_restaurant": {
        "value": "Vietnamese restaurant",
        "sourceType": "manual",
        "sourceUrl": "https://discord.com/channels/1493925728570310756/1502385333155926027",
        "confidence": 0.72,
        "scrapedAt": "2026-05-08T19:18:58.370Z",
        "extractor": "discord_google_maps_discovery"
      },
      "casual_dining": {
        "value": "casual dining",
        "sourceType": "manual",
        "sourceUrl": "https://discord.com/channels/1493925728570310756/1502385333155926027",
        "confidence": 0.72,
        "scrapedAt": "2026-05-08T19:18:58.370Z",
        "extractor": "discord_google_maps_discovery"
      },
      "takeaway": {
        "value": "takeaway",
        "sourceType": "manual",
        "sourceUrl": "https://discord.com/channels/1493925728570310756/1502385333155926027",
        "confidence": 0.72,
        "scrapedAt": "2026-05-08T19:18:58.370Z",
        "extractor": "discord_google_maps_discovery"
      }
    },
    "opportunity": {
      "noDedicatedWebsiteFound": {
        "value": "true",
        "sourceType": "manual",
        "sourceUrl": "https://discord.com/channels/1493925728570310756/1502385333155926027",
        "confidence": 0.72,
        "scrapedAt": "2026-05-08T19:18:58.370Z",
        "extractor": "discord_google_maps_discovery"
      }
    }
  }
}
