[
  {
    "sourceType": "maps_scraper",
    "leadId": "0xaa7a33159a26fbf7:0xf5a4e56f5038a44f",
    "place_id": "",
    "cid": "",
    "data_id": "0xaa7a33159a26fbf7:0xf5a4e56f5038a44f",
    "name": "Alex McPherson Electrical",
    "category": "",
    "categories": [],
    "address": "131 Tarleton St, East Devonport TAS 7310",
    "city": "devonport",
    "niche": "electrician",
    "phone": "(03)64277771",
    "website": "",
    "google_maps_url": "",
    "rating": 4.6,
    "review_count": 0,
    "latitude": -41.18275,
    "longitude": 146.372718,
    "timezone": "Australia/Hobart",
    "price_range": "",
    "websiteStatus": "no_website",
    "discoveryScore": 70,
    "relevance": {
      "relevant": true,
      "reason": "no_relevance_rule",
      "matched": []
    },
    "recommendedAction": "starter_candidate",
    "signals": {
      "hasPhone": true,
      "hasWebsite": false,
      "hasMenuLink": true,
      "hasReservationLink": true,
      "hasOrderOnlineLink": true,
      "imageCount": 0,
      "hasPopularTimes": true,
      "hasAboutAttributes": false
    },
    "sourceQuery": "electrician in devonport"
  },
  {
    "sourceType": "maps_scraper",
    "leadId": "0xaa7bccb121d3ffff:0xee461b30030b5436",
    "place_id": "",
    "cid": "",
    "data_id": "0xaa7bccb121d3ffff:0xee461b30030b5436",
    "name": "COLDY'S ELECTRICAL",
    "category": "",
    "categories": [],
    "address": "25 Watkinson St, Devonport TAS 7310",
    "city": "devonport",
    "niche": "electrician",
    "phone": "0437778099",
    "website": "",
    "google_maps_url": "",
    "rating": 0,
    "review_count": 0,
    "latitude": -41.17817,
    "longitude": 146.332115,
    "timezone": "Australia/Hobart",
    "price_range": "",
    "websiteStatus": "no_website",
    "discoveryScore": 62,
    "relevance": {
      "relevant": true,
      "reason": "no_relevance_rule",
      "matched": []
    },
    "recommendedAction": "starter_candidate",
    "signals": {
      "hasPhone": true,
      "hasWebsite": false,
      "hasMenuLink": true,
      "hasReservationLink": true,
      "hasOrderOnlineLink": true,
      "imageCount": 0,
      "hasPopularTimes": true,
      "hasAboutAttributes": false
    },
    "sourceQuery": "electrician in devonport"
  },
  {
    "sourceType": "maps_scraper",
    "leadId": "0xaa7a3368232bec05:0xd69b3d38dd28bf0a",
    "place_id": "",
    "cid": "",
    "data_id": "0xaa7a3368232bec05:0xd69b3d38dd28bf0a",
    "name": "M5 Electrical Pty Ltd",
    "category": "",
    "categories": [],
    "address": "5 Finlaysons Way, Devonport TAS 7310",
    "city": "devonport",
    "niche": "electrician",
    "phone": "(03)64233444",
    "website": "http://www.m5electrical.com.au/",
    "google_maps_url": "",
    "rating": 4.9,
    "review_count": 0,
    "latitude": -41.18996,
    "longitude": 146.362428,
    "timezone": "Australia/Hobart",
    "price_range": "",
    "websiteStatus": "independent_http_site",
    "discoveryScore": 54,
    "relevance": {
      "relevant": true,
      "reason": "no_relevance_rule",
      "matched": []
    },
    "recommendedAction": "skip",
    "signals": {
      "hasPhone": true,
      "hasWebsite": true,
      "hasMenuLink": true,
      "hasReservationLink": true,
      "hasOrderOnlineLink": true,
      "imageCount": 0,
      "hasPopularTimes": true,
      "hasAboutAttributes": false
    },
    "sourceQuery": "electrician in devonport"
  },
  {
    "sourceType": "maps_scraper",
    "leadId": "0xaa7bccaecd2dfe05:0xf121e2407e6ec528",
    "place_id": "",
    "cid": "",
    "data_id": "0xaa7bccaecd2dfe05:0xf121e2407e6ec528",
    "name": "DES Electrical & Solar",
    "category": "",
    "categories": [],
    "address": "113 Don Rd, Devonport TAS 7310",
    "city": "devonport",
    "niche": "electrician",
    "phone": "(03)64249002",
    "website": "http://www.deselec.com.au/",
    "google_maps_url": "",
    "rating": 4.8,
    "review_count": 0,
    "latitude": -41.184211,
    "longitude": 146.325131,
    "timezone": "Australia/Hobart",
    "price_range": "",
    "websiteStatus": "independent_http_site",
    "discoveryScore": 54,
    "relevance": {
      "relevant": true,
      "reason": "no_relevance_rule",
      "matched": []
    },
    "recommendedAction": "skip",
    "signals": {
      "hasPhone": true,
      "hasWebsite": true,
      "hasMenuLink": true,
      "hasReservationLink": true,
      "hasOrderOnlineLink": true,
      "imageCount": 0,
      "hasPopularTimes": true,
      "hasAboutAttributes": false
    },
    "sourceQuery": "electrician in devonport"
  },
  {
    "sourceType": "maps_scraper",
    "leadId": "0xaa7a349ea38b4671:0xd281ec512a6ebe08",
    "place_id": "",
    "cid": "",
    "data_id": "0xaa7a349ea38b4671:0xd281ec512a6ebe08",
    "name": "Mainwaring Auto Electrics",
    "category": "",
    "categories": [],
    "address": "5 Devonport Rd, Miandetta TAS 7310",
    "city": "devonport",
    "niche": "electrician",
    "phone": "(03)64243352",
    "website": "http://www.mainwarings.com.au/",
    "google_maps_url": "",
    "rating": 4.3,
    "review_count": 0,
    "latitude": -41.192717,
    "longitude": 146.364164,
    "timezone": "Australia/Hobart",
    "price_range": "",
    "websiteStatus": "independent_http_site",
    "discoveryScore": 50,
    "relevance": {
      "relevant": true,
      "reason": "no_relevance_rule",
      "matched": []
    },
    "recommendedAction": "skip",
    "signals": {
      "hasPhone": true,
      "hasWebsite": true,
      "hasMenuLink": true,
      "hasReservationLink": true,
      "hasOrderOnlineLink": true,
      "imageCount": 0,
      "hasPopularTimes": true,
      "hasAboutAttributes": false
    },
    "sourceQuery": "electrician in devonport"
  },
  {
    "sourceType": "maps_scraper",
    "leadId": "0xaa7a334b97f0ba17:0x86ee849d7a4335a8",
    "place_id": "",
    "cid": "",
    "data_id": "0xaa7a334b97f0ba17:0x86ee849d7a4335a8",
    "name": "Atkinson Electrical",
    "category": "",
    "categories": [],
    "address": "Devonport TAS 7310",
    "city": "devonport",
    "niche": "electrician",
    "phone": "0409532456",
    "website": "http://www.atkinsonelectrical.com.au/",
    "google_maps_url": "",
    "rating": 3.2,
    "review_count": 0,
    "latitude": -41.178353,
    "longitude": 146.360953,
    "timezone": "Australia/Hobart",
    "price_range": "",
    "websiteStatus": "independent_http_site",
    "discoveryScore": 42,
    "relevance": {
      "relevant": true,
      "reason": "no_relevance_rule",
      "matched": []
    },
    "recommendedAction": "skip",
    "signals": {
      "hasPhone": true,
      "hasWebsite": true,
      "hasMenuLink": true,
      "hasReservationLink": true,
      "hasOrderOnlineLink": true,
      "imageCount": 0,
      "hasPopularTimes": true,
      "hasAboutAttributes": false
    },
    "sourceQuery": "electrician in devonport"
  },
  {
    "sourceType": "maps_scraper",
    "leadId": "0xaa7a33476955a399:0x11f08ad00151456d",
    "place_id": "",
    "cid": "",
    "data_id": "0xaa7a33476955a399:0x11f08ad00151456d",
    "name": "Rexel Electrical Supplies Devonport",
    "category": "",
    "categories": [],
    "address": "14 Wenvoe St, Devonport TAS 7310",
    "city": "devonport",
    "niche": "electrician",
    "phone": "(03)64244433",
    "website": "https://www.rexel.com.au/are/Devonport/store/7161",
    "google_maps_url": "",
    "rating": 5,
    "review_count": 0,
    "latitude": -41.18259,
    "longitude": 146.36084,
    "timezone": "Australia/Hobart",
    "price_range": "",
    "websiteStatus": "independent_https_site",
    "discoveryScore": 34,
    "relevance": {
      "relevant": true,
      "reason": "no_relevance_rule",
      "matched": []
    },
    "recommendedAction": "skip",
    "signals": {
      "hasPhone": true,
      "hasWebsite": true,
      "hasMenuLink": true,
      "hasReservationLink": true,
      "hasOrderOnlineLink": true,
      "imageCount": 0,
      "hasPopularTimes": true,
      "hasAboutAttributes": false
    },
    "sourceQuery": "electrician in devonport"
  },
  {
    "sourceType": "maps_scraper",
    "leadId": "0x4deb0706e14913ad:0xd3d017991dd87285",
    "place_id": "",
    "cid": "",
    "data_id": "0x4deb0706e14913ad:0xd3d017991dd87285",
    "name": "Buzzzed Electrical",
    "category": "",
    "categories": [],
    "address": "Shed E/45A Elizabeth St, Devonport TAS 7310",
    "city": "devonport",
    "niche": "electrician",
    "phone": "0483931647",
    "website": "https://www.buzzzed.com.au/",
    "google_maps_url": "",
    "rating": 4.8,
    "review_count": 0,
    "latitude": -41.189971,
    "longitude": 146.356028,
    "timezone": "Australia/Hobart",
    "price_range": "",
    "websiteStatus": "independent_https_site",
    "discoveryScore": 34,
    "relevance": {
      "relevant": true,
      "reason": "no_relevance_rule",
      "matched": []
    },
    "recommendedAction": "skip",
    "signals": {
      "hasPhone": true,
      "hasWebsite": true,
      "hasMenuLink": true,
      "hasReservationLink": true,
      "hasOrderOnlineLink": true,
      "imageCount": 0,
      "hasPopularTimes": true,
      "hasAboutAttributes": false
    },
    "sourceQuery": "electrician in devonport"
  },
  {
    "sourceType": "maps_scraper",
    "leadId": "0xaa7bccb22de998e3:0xf0c64825a5161879",
    "place_id": "",
    "cid": "",
    "data_id": "0xaa7bccb22de998e3:0xf0c64825a5161879",
    "name": "D&W Electrical Devonport",
    "category": "",
    "categories": [],
    "address": "39a Don Rd, Devonport TAS 7310",
    "city": "devonport",
    "niche": "electrician",
    "phone": "(03)64244522",
    "website": "https://dw.mmem.com.au/devonport?utm_term=plcid_16140536226756377667",
    "google_maps_url": "",
    "rating": 5,
    "review_count": 0,
    "latitude": -41.18131,
    "longitude": 146.333783,
    "timezone": "Australia/Hobart",
    "price_range": "",
    "websiteStatus": "independent_https_site",
    "discoveryScore": 34,
    "relevance": {
      "relevant": true,
      "reason": "no_relevance_rule",
      "matched": []
    },
    "recommendedAction": "skip",
    "signals": {
      "hasPhone": true,
      "hasWebsite": true,
      "hasMenuLink": true,
      "hasReservationLink": true,
      "hasOrderOnlineLink": true,
      "imageCount": 0,
      "hasPopularTimes": true,
      "hasAboutAttributes": false
    },
    "sourceQuery": "electrician in devonport"
  },
  {
    "sourceType": "maps_scraper",
    "leadId": "0xaa7a3340b3bcd55f:0xc81b6426a54610b0",
    "place_id": "",
    "cid": "",
    "data_id": "0xaa7a3340b3bcd55f:0xc81b6426a54610b0",
    "name": "Tones Solar & Electrical Devonport",
    "category": "",
    "categories": [],
    "address": "124 Tarleton St, East Devonport TAS 7310",
    "city": "devonport",
    "niche": "electrician",
    "phone": "1300985985",
    "website": "https://toneselectrical.com.au/",
    "google_maps_url": "",
    "rating": 5,
    "review_count": 0,
    "latitude": -41.183966,
    "longitude": 146.371595,
    "timezone": "Australia/Hobart",
    "price_range": "",
    "websiteStatus": "independent_https_site",
    "discoveryScore": 34,
    "relevance": {
      "relevant": true,
      "reason": "no_relevance_rule",
      "matched": []
    },
    "recommendedAction": "skip",
    "signals": {
      "hasPhone": true,
      "hasWebsite": true,
      "hasMenuLink": true,
      "hasReservationLink": true,
      "hasOrderOnlineLink": true,
      "imageCount": 0,
      "hasPopularTimes": true,
      "hasAboutAttributes": false
    },
    "sourceQuery": "electrician in devonport"
  },
  {
    "sourceType": "maps_scraper",
    "leadId": "0xaa7a349168d3d5b9:0x891452dfcb83c84c",
    "place_id": "",
    "cid": "",
    "data_id": "0xaa7a349168d3d5b9:0x891452dfcb83c84c",
    "name": "RBD Electrical - Devonport & Northern Tasmania",
    "category": "",
    "categories": [],
    "address": "3 Bay Dr, Quoiba TAS 7310",
    "city": "devonport",
    "niche": "electrician",
    "phone": "(03)64272678",
    "website": "https://rbdelectrical.com.au/",
    "google_maps_url": "",
    "rating": 5,
    "review_count": 0,
    "latitude": -41.20967,
    "longitude": 146.346604,
    "timezone": "Australia/Hobart",
    "price_range": "",
    "websiteStatus": "independent_https_site",
    "discoveryScore": 34,
    "relevance": {
      "relevant": true,
      "reason": "no_relevance_rule",
      "matched": []
    },
    "recommendedAction": "skip",
    "signals": {
      "hasPhone": true,
      "hasWebsite": true,
      "hasMenuLink": true,
      "hasReservationLink": true,
      "hasOrderOnlineLink": true,
      "imageCount": 0,
      "hasPopularTimes": true,
      "hasAboutAttributes": false
    },
    "sourceQuery": "electrician in devonport"
  },
  {
    "sourceType": "maps_scraper",
    "leadId": "0xaf02a2f6ddef6fcd:0xd1c71b458d1976a9",
    "place_id": "",
    "cid": "",
    "data_id": "0xaf02a2f6ddef6fcd:0xd1c71b458d1976a9",
    "name": "DKL Electrical & Heating",
    "category": "",
    "categories": [],
    "address": "57C Kelcey Tier Rd, Spreyton TAS 7310",
    "city": "devonport",
    "niche": "electrician",
    "phone": "0466446543",
    "website": "https://www.dklelectrical.com.au/",
    "google_maps_url": "",
    "rating": 4.9,
    "review_count": 0,
    "latitude": -41.220797,
    "longitude": 146.340498,
    "timezone": "Australia/Hobart",
    "price_range": "",
    "websiteStatus": "independent_https_site",
    "discoveryScore": 34,
    "relevance": {
      "relevant": true,
      "reason": "no_relevance_rule",
      "matched": []
    },
    "recommendedAction": "skip",
    "signals": {
      "hasPhone": true,
      "hasWebsite": true,
      "hasMenuLink": true,
      "hasReservationLink": true,
      "hasOrderOnlineLink": true,
      "imageCount": 0,
      "hasPopularTimes": true,
      "hasAboutAttributes": false
    },
    "sourceQuery": "electrician in devonport"
  }
]
