{
  "deliverableId": "m1-d2-discovery-score",
  "overall": "PASS",
  "total": 7,
  "passed": 7,
  "skipped": 0,
  "failed": 0,
  "took_ms": 3,
  "ran_at": "2026-05-13T07:07:10.666Z",
  "results": [
    {
      "name": "case-gosom-full",
      "passed": true,
      "error": null,
      "took_ms": 0
    },
    {
      "name": "case-places-full",
      "passed": true,
      "error": null,
      "took_ms": 0
    },
    {
      "name": "case-image-min",
      "passed": true,
      "error": null,
      "took_ms": 0
    },
    {
      "name": "case-single-enrich",
      "passed": true,
      "error": null,
      "took_ms": 0
    },
    {
      "name": "case-no-website-bonus",
      "passed": true,
      "error": null,
      "took_ms": 0
    },
    {
      "name": "case-empty-no-crash",
      "passed": true,
      "error": null,
      "took_ms": 0
    },
    {
      "name": "classify-website-status-shared",
      "passed": true,
      "error": null,
      "took_ms": 0
    }
  ],
  "scores": {
    "gosom-full": 38,
    "places-full": 38,
    "image-min": 0,
    "single-enrich": 35,
    "no-website-bonus": 55,
    "empty-no-crash": 0
  }
}