{
  "schemaVersion": 1,
  "generatedAt": "2026-05-14T08:30:28.388Z",
  "runId": "20260514-183028",
  "query": "roofer in perth",
  "niche": "roofer",
  "city": "perth",
  "batchId": "",
  "costPolicy": {
    "googlePlacesApi": "not_used_in_discovery",
    "emailExtraction": "disabled",
    "reviewBodyExtraction": "disabled",
    "reviewPayloadStorage": "stripped_before_analysis",
    "proxy": "none",
    "notes": [
      "Use maps scraper for cheap broad discovery.",
      "Use Google Places API only after a candidate is selected for official verification/evidence.",
      "Use Tinyfish/site-audit only for selected website audit candidates.",
      "The upstream scraper may return small default review samples; this workflow strips review/email payloads before analysis storage unless explicitly overridden."
    ]
  },
  "toolLog": {
    "tool": "gosom/google-maps-scraper",
    "toolVersion": "docker:gosom/google-maps-scraper:latest",
    "command": "",
    "rawPath": "data/maps-scraper/runs/20260514-183028/results.maps.json",
    "proxy": "none",
    "googlePlacesApi": "not_used",
    "emailExtraction": "disabled",
    "reviewBodyExtraction": "disabled",
    "reviewPayloadStorage": "stripped_before_analysis",
    "docker": null
  },
  "totals": {
    "rawRows": 8,
    "leads": 8,
    "withWebsite": 8,
    "withPhone": 8,
    "actionCounts": {
      "skip": 8
    },
    "websiteStatusCounts": {
      "independent_http_site": 1,
      "independent_https_site": 7
    }
  },
  "queue": {
    "starterCandidates": [],
    "auditCandidates": [],
    "manualReview": [],
    "skipped": [
      {
        "sourceType": "maps_scraper",
        "leadId": "0x2a32afd3575b324d:0xb8e76c6227d746ca",
        "place_id": "",
        "cid": "",
        "data_id": "0x2a32afd3575b324d:0xb8e76c6227d746ca",
        "name": "Prompt Roofing",
        "category": "",
        "categories": [],
        "address": "U2/54 O'Malley St, Osborne Park WA 6017",
        "city": "perth",
        "niche": "roofer",
        "phone": "0433210028",
        "website": "http://www.promptroofing.com.au/",
        "google_maps_url": "",
        "rating": 4.8,
        "review_count": 0,
        "latitude": -31.900727,
        "longitude": 115.813495,
        "timezone": "Australia/Perth",
        "price_range": "",
        "websiteStatus": "independent_http_site",
        "discoveryScore": 54,
        "relevance": {
          "relevant": true,
          "reason": "matched_category_or_name",
          "matched": [
            "roof"
          ]
        },
        "recommendedAction": "skip",
        "signals": {
          "hasPhone": true,
          "hasWebsite": true,
          "hasMenuLink": true,
          "hasReservationLink": true,
          "hasOrderOnlineLink": true,
          "imageCount": 0,
          "hasPopularTimes": true,
          "hasAboutAttributes": false
        },
        "sourceQuery": "roofer in perth"
      },
      {
        "sourceType": "maps_scraper",
        "leadId": "0x2a32bad95d90b60b:0x296740e9f50b5a59",
        "place_id": "",
        "cid": "",
        "data_id": "0x2a32bad95d90b60b:0x296740e9f50b5a59",
        "name": "Perth Roofing & Gutters",
        "category": "",
        "categories": [],
        "address": "9/71 Parry St, Perth WA 6000",
        "city": "perth",
        "niche": "roofer",
        "phone": "(08)62451204",
        "website": "https://www.perthroofingandgutters.com.au/?utm_source=google&utm_medium=organic&utm_campaign=gbp",
        "google_maps_url": "",
        "rating": 4.7,
        "review_count": 0,
        "latitude": -31.948744,
        "longitude": 115.868506,
        "timezone": "Australia/Perth",
        "price_range": "",
        "websiteStatus": "independent_https_site",
        "discoveryScore": 34,
        "relevance": {
          "relevant": true,
          "reason": "matched_category_or_name",
          "matched": [
            "roof",
            "gutter"
          ]
        },
        "recommendedAction": "skip",
        "signals": {
          "hasPhone": true,
          "hasWebsite": true,
          "hasMenuLink": true,
          "hasReservationLink": true,
          "hasOrderOnlineLink": true,
          "imageCount": 0,
          "hasPopularTimes": true,
          "hasAboutAttributes": false
        },
        "sourceQuery": "roofer in perth"
      },
      {
        "sourceType": "maps_scraper",
        "leadId": "0xaf3b0486fc809b6f:0x5a7f5e0cef718629",
        "place_id": "",
        "cid": "",
        "data_id": "0xaf3b0486fc809b6f:0x5a7f5e0cef718629",
        "name": "Prime Roofing and Gutters",
        "category": "",
        "categories": [],
        "address": "Level 25/1 Spring St, Perth WA 6000",
        "city": "perth",
        "niche": "roofer",
        "phone": "0489076877",
        "website": "https://www.primeroofingperth.com/",
        "google_maps_url": "",
        "rating": 4.9,
        "review_count": 0,
        "latitude": -31.954822,
        "longitude": 115.850335,
        "timezone": "Australia/Perth",
        "price_range": "",
        "websiteStatus": "independent_https_site",
        "discoveryScore": 34,
        "relevance": {
          "relevant": true,
          "reason": "matched_category_or_name",
          "matched": [
            "roof",
            "gutter"
          ]
        },
        "recommendedAction": "skip",
        "signals": {
          "hasPhone": true,
          "hasWebsite": true,
          "hasMenuLink": true,
          "hasReservationLink": true,
          "hasOrderOnlineLink": true,
          "imageCount": 0,
          "hasPopularTimes": true,
          "hasAboutAttributes": false
        },
        "sourceQuery": "roofer in perth"
      },
      {
        "sourceType": "maps_scraper",
        "leadId": "0x2a32a5c27ce813dd:0x6a53bc65d1542d26",
        "place_id": "",
        "cid": "",
        "data_id": "0x2a32a5c27ce813dd:0x6a53bc65d1542d26",
        "name": "Perth Local Roofers",
        "category": "",
        "categories": [],
        "address": "443A Cambridge St, Floreat WA 6014",
        "city": "perth",
        "niche": "roofer",
        "phone": "(08)75628884",
        "website": "https://perthlocalroofers.com.au/",
        "google_maps_url": "",
        "rating": 5,
        "review_count": 0,
        "latitude": -31.941126,
        "longitude": 115.801609,
        "timezone": "Australia/Perth",
        "price_range": "",
        "websiteStatus": "independent_https_site",
        "discoveryScore": 34,
        "relevance": {
          "relevant": true,
          "reason": "matched_category_or_name",
          "matched": [
            "roof"
          ]
        },
        "recommendedAction": "skip",
        "signals": {
          "hasPhone": true,
          "hasWebsite": true,
          "hasMenuLink": true,
          "hasReservationLink": true,
          "hasOrderOnlineLink": true,
          "imageCount": 0,
          "hasPopularTimes": true,
          "hasAboutAttributes": false
        },
        "sourceQuery": "roofer in perth"
      },
      {
        "sourceType": "maps_scraper",
        "leadId": "0x2bcd53c64719a25b:0x39dee1fc49802cfe",
        "place_id": "",
        "cid": "",
        "data_id": "0x2bcd53c64719a25b:0x39dee1fc49802cfe",
        "name": "Powerdrive Roofing",
        "category": "",
        "categories": [],
        "address": "",
        "city": "perth",
        "niche": "roofer",
        "phone": "0421768842",
        "website": "https://powerdriveroofing.com.au/",
        "google_maps_url": "",
        "rating": 4.9,
        "review_count": 0,
        "latitude": -31.956645,
        "longitude": 115.932308,
        "timezone": "Australia/Perth",
        "price_range": "",
        "websiteStatus": "independent_https_site",
        "discoveryScore": 34,
        "relevance": {
          "relevant": true,
          "reason": "matched_category_or_name",
          "matched": [
            "roof"
          ]
        },
        "recommendedAction": "skip",
        "signals": {
          "hasPhone": true,
          "hasWebsite": true,
          "hasMenuLink": true,
          "hasReservationLink": true,
          "hasOrderOnlineLink": true,
          "imageCount": 0,
          "hasPopularTimes": true,
          "hasAboutAttributes": false
        },
        "sourceQuery": "roofer in perth"
      },
      {
        "sourceType": "maps_scraper",
        "leadId": "0x2da32cc24e05500f:0x248afc17ce45c584",
        "place_id": "",
        "cid": "",
        "data_id": "0x2da32cc24e05500f:0x248afc17ce45c584",
        "name": "Perth Re-Roofing",
        "category": "",
        "categories": [],
        "address": "6/83 Hector St W, Osborne Park WA 6017",
        "city": "perth",
        "niche": "roofer",
        "phone": "(08)65566600",
        "website": "https://www.perthreroofing.com.au/?utm_source=google&utm_medium=organic&utm_campaign=gmb",
        "google_maps_url": "",
        "rating": 5,
        "review_count": 0,
        "latitude": -31.901391,
        "longitude": 115.817885,
        "timezone": "Australia/Perth",
        "price_range": "",
        "websiteStatus": "independent_https_site",
        "discoveryScore": 34,
        "relevance": {
          "relevant": true,
          "reason": "matched_category_or_name",
          "matched": [
            "roof"
          ]
        },
        "recommendedAction": "skip",
        "signals": {
          "hasPhone": true,
          "hasWebsite": true,
          "hasMenuLink": true,
          "hasReservationLink": true,
          "hasOrderOnlineLink": true,
          "imageCount": 0,
          "hasPopularTimes": true,
          "hasAboutAttributes": false
        },
        "sourceQuery": "roofer in perth"
      },
      {
        "sourceType": "maps_scraper",
        "leadId": "0x82f6e83428987831:0xd87607388bf96ef3",
        "place_id": "",
        "cid": "",
        "data_id": "0x82f6e83428987831:0xd87607388bf96ef3",
        "name": "Virtue Roofing WA Pty Ltd",
        "category": "",
        "categories": [],
        "address": "Unit 4/41 Sarich Ct, Osborne Park WA 6017",
        "city": "perth",
        "niche": "roofer",
        "phone": "(08)65568853",
        "website": "https://virtueroofing.com.au/",
        "google_maps_url": "",
        "rating": 5,
        "review_count": 0,
        "latitude": -31.897493,
        "longitude": 115.810813,
        "timezone": "Australia/Perth",
        "price_range": "",
        "websiteStatus": "independent_https_site",
        "discoveryScore": 34,
        "relevance": {
          "relevant": true,
          "reason": "matched_category_or_name",
          "matched": [
            "roof"
          ]
        },
        "recommendedAction": "skip",
        "signals": {
          "hasPhone": true,
          "hasWebsite": true,
          "hasMenuLink": true,
          "hasReservationLink": true,
          "hasOrderOnlineLink": true,
          "imageCount": 0,
          "hasPopularTimes": true,
          "hasAboutAttributes": false
        },
        "sourceQuery": "roofer in perth"
      },
      {
        "sourceType": "maps_scraper",
        "leadId": "0x875f805443d4e56d:0xa2eba4eb4b7eb5ba",
        "place_id": "",
        "cid": "",
        "data_id": "0x875f805443d4e56d:0xa2eba4eb4b7eb5ba",
        "name": "SOS Roofing",
        "category": "",
        "categories": [],
        "address": "Chaucer St, Yokine WA 6060",
        "city": "perth",
        "niche": "roofer",
        "phone": "(08)62855700",
        "website": "https://www.sos-roofing.com.au/",
        "google_maps_url": "",
        "rating": 4.6,
        "review_count": 0,
        "latitude": -31.90516,
        "longitude": 115.856838,
        "timezone": "Australia/Perth",
        "price_range": "",
        "websiteStatus": "independent_https_site",
        "discoveryScore": 30,
        "relevance": {
          "relevant": true,
          "reason": "matched_category_or_name",
          "matched": [
            "roof"
          ]
        },
        "recommendedAction": "skip",
        "signals": {
          "hasPhone": true,
          "hasWebsite": true,
          "hasMenuLink": true,
          "hasReservationLink": true,
          "hasOrderOnlineLink": true,
          "imageCount": 0,
          "hasPopularTimes": true,
          "hasAboutAttributes": false
        },
        "sourceQuery": "roofer in perth"
      }
    ]
  },
  "leads": [
    {
      "sourceType": "maps_scraper",
      "leadId": "0x2a32afd3575b324d:0xb8e76c6227d746ca",
      "place_id": "",
      "cid": "",
      "data_id": "0x2a32afd3575b324d:0xb8e76c6227d746ca",
      "name": "Prompt Roofing",
      "category": "",
      "categories": [],
      "address": "U2/54 O'Malley St, Osborne Park WA 6017",
      "city": "perth",
      "niche": "roofer",
      "phone": "0433210028",
      "website": "http://www.promptroofing.com.au/",
      "google_maps_url": "",
      "rating": 4.8,
      "review_count": 0,
      "latitude": -31.900727,
      "longitude": 115.813495,
      "timezone": "Australia/Perth",
      "price_range": "",
      "websiteStatus": "independent_http_site",
      "discoveryScore": 54,
      "relevance": {
        "relevant": true,
        "reason": "matched_category_or_name",
        "matched": [
          "roof"
        ]
      },
      "recommendedAction": "skip",
      "signals": {
        "hasPhone": true,
        "hasWebsite": true,
        "hasMenuLink": true,
        "hasReservationLink": true,
        "hasOrderOnlineLink": true,
        "imageCount": 0,
        "hasPopularTimes": true,
        "hasAboutAttributes": false
      },
      "sourceQuery": "roofer in perth"
    },
    {
      "sourceType": "maps_scraper",
      "leadId": "0x2a32bad95d90b60b:0x296740e9f50b5a59",
      "place_id": "",
      "cid": "",
      "data_id": "0x2a32bad95d90b60b:0x296740e9f50b5a59",
      "name": "Perth Roofing & Gutters",
      "category": "",
      "categories": [],
      "address": "9/71 Parry St, Perth WA 6000",
      "city": "perth",
      "niche": "roofer",
      "phone": "(08)62451204",
      "website": "https://www.perthroofingandgutters.com.au/?utm_source=google&utm_medium=organic&utm_campaign=gbp",
      "google_maps_url": "",
      "rating": 4.7,
      "review_count": 0,
      "latitude": -31.948744,
      "longitude": 115.868506,
      "timezone": "Australia/Perth",
      "price_range": "",
      "websiteStatus": "independent_https_site",
      "discoveryScore": 34,
      "relevance": {
        "relevant": true,
        "reason": "matched_category_or_name",
        "matched": [
          "roof",
          "gutter"
        ]
      },
      "recommendedAction": "skip",
      "signals": {
        "hasPhone": true,
        "hasWebsite": true,
        "hasMenuLink": true,
        "hasReservationLink": true,
        "hasOrderOnlineLink": true,
        "imageCount": 0,
        "hasPopularTimes": true,
        "hasAboutAttributes": false
      },
      "sourceQuery": "roofer in perth"
    },
    {
      "sourceType": "maps_scraper",
      "leadId": "0xaf3b0486fc809b6f:0x5a7f5e0cef718629",
      "place_id": "",
      "cid": "",
      "data_id": "0xaf3b0486fc809b6f:0x5a7f5e0cef718629",
      "name": "Prime Roofing and Gutters",
      "category": "",
      "categories": [],
      "address": "Level 25/1 Spring St, Perth WA 6000",
      "city": "perth",
      "niche": "roofer",
      "phone": "0489076877",
      "website": "https://www.primeroofingperth.com/",
      "google_maps_url": "",
      "rating": 4.9,
      "review_count": 0,
      "latitude": -31.954822,
      "longitude": 115.850335,
      "timezone": "Australia/Perth",
      "price_range": "",
      "websiteStatus": "independent_https_site",
      "discoveryScore": 34,
      "relevance": {
        "relevant": true,
        "reason": "matched_category_or_name",
        "matched": [
          "roof",
          "gutter"
        ]
      },
      "recommendedAction": "skip",
      "signals": {
        "hasPhone": true,
        "hasWebsite": true,
        "hasMenuLink": true,
        "hasReservationLink": true,
        "hasOrderOnlineLink": true,
        "imageCount": 0,
        "hasPopularTimes": true,
        "hasAboutAttributes": false
      },
      "sourceQuery": "roofer in perth"
    },
    {
      "sourceType": "maps_scraper",
      "leadId": "0x2a32a5c27ce813dd:0x6a53bc65d1542d26",
      "place_id": "",
      "cid": "",
      "data_id": "0x2a32a5c27ce813dd:0x6a53bc65d1542d26",
      "name": "Perth Local Roofers",
      "category": "",
      "categories": [],
      "address": "443A Cambridge St, Floreat WA 6014",
      "city": "perth",
      "niche": "roofer",
      "phone": "(08)75628884",
      "website": "https://perthlocalroofers.com.au/",
      "google_maps_url": "",
      "rating": 5,
      "review_count": 0,
      "latitude": -31.941126,
      "longitude": 115.801609,
      "timezone": "Australia/Perth",
      "price_range": "",
      "websiteStatus": "independent_https_site",
      "discoveryScore": 34,
      "relevance": {
        "relevant": true,
        "reason": "matched_category_or_name",
        "matched": [
          "roof"
        ]
      },
      "recommendedAction": "skip",
      "signals": {
        "hasPhone": true,
        "hasWebsite": true,
        "hasMenuLink": true,
        "hasReservationLink": true,
        "hasOrderOnlineLink": true,
        "imageCount": 0,
        "hasPopularTimes": true,
        "hasAboutAttributes": false
      },
      "sourceQuery": "roofer in perth"
    },
    {
      "sourceType": "maps_scraper",
      "leadId": "0x2bcd53c64719a25b:0x39dee1fc49802cfe",
      "place_id": "",
      "cid": "",
      "data_id": "0x2bcd53c64719a25b:0x39dee1fc49802cfe",
      "name": "Powerdrive Roofing",
      "category": "",
      "categories": [],
      "address": "",
      "city": "perth",
      "niche": "roofer",
      "phone": "0421768842",
      "website": "https://powerdriveroofing.com.au/",
      "google_maps_url": "",
      "rating": 4.9,
      "review_count": 0,
      "latitude": -31.956645,
      "longitude": 115.932308,
      "timezone": "Australia/Perth",
      "price_range": "",
      "websiteStatus": "independent_https_site",
      "discoveryScore": 34,
      "relevance": {
        "relevant": true,
        "reason": "matched_category_or_name",
        "matched": [
          "roof"
        ]
      },
      "recommendedAction": "skip",
      "signals": {
        "hasPhone": true,
        "hasWebsite": true,
        "hasMenuLink": true,
        "hasReservationLink": true,
        "hasOrderOnlineLink": true,
        "imageCount": 0,
        "hasPopularTimes": true,
        "hasAboutAttributes": false
      },
      "sourceQuery": "roofer in perth"
    },
    {
      "sourceType": "maps_scraper",
      "leadId": "0x2da32cc24e05500f:0x248afc17ce45c584",
      "place_id": "",
      "cid": "",
      "data_id": "0x2da32cc24e05500f:0x248afc17ce45c584",
      "name": "Perth Re-Roofing",
      "category": "",
      "categories": [],
      "address": "6/83 Hector St W, Osborne Park WA 6017",
      "city": "perth",
      "niche": "roofer",
      "phone": "(08)65566600",
      "website": "https://www.perthreroofing.com.au/?utm_source=google&utm_medium=organic&utm_campaign=gmb",
      "google_maps_url": "",
      "rating": 5,
      "review_count": 0,
      "latitude": -31.901391,
      "longitude": 115.817885,
      "timezone": "Australia/Perth",
      "price_range": "",
      "websiteStatus": "independent_https_site",
      "discoveryScore": 34,
      "relevance": {
        "relevant": true,
        "reason": "matched_category_or_name",
        "matched": [
          "roof"
        ]
      },
      "recommendedAction": "skip",
      "signals": {
        "hasPhone": true,
        "hasWebsite": true,
        "hasMenuLink": true,
        "hasReservationLink": true,
        "hasOrderOnlineLink": true,
        "imageCount": 0,
        "hasPopularTimes": true,
        "hasAboutAttributes": false
      },
      "sourceQuery": "roofer in perth"
    },
    {
      "sourceType": "maps_scraper",
      "leadId": "0x82f6e83428987831:0xd87607388bf96ef3",
      "place_id": "",
      "cid": "",
      "data_id": "0x82f6e83428987831:0xd87607388bf96ef3",
      "name": "Virtue Roofing WA Pty Ltd",
      "category": "",
      "categories": [],
      "address": "Unit 4/41 Sarich Ct, Osborne Park WA 6017",
      "city": "perth",
      "niche": "roofer",
      "phone": "(08)65568853",
      "website": "https://virtueroofing.com.au/",
      "google_maps_url": "",
      "rating": 5,
      "review_count": 0,
      "latitude": -31.897493,
      "longitude": 115.810813,
      "timezone": "Australia/Perth",
      "price_range": "",
      "websiteStatus": "independent_https_site",
      "discoveryScore": 34,
      "relevance": {
        "relevant": true,
        "reason": "matched_category_or_name",
        "matched": [
          "roof"
        ]
      },
      "recommendedAction": "skip",
      "signals": {
        "hasPhone": true,
        "hasWebsite": true,
        "hasMenuLink": true,
        "hasReservationLink": true,
        "hasOrderOnlineLink": true,
        "imageCount": 0,
        "hasPopularTimes": true,
        "hasAboutAttributes": false
      },
      "sourceQuery": "roofer in perth"
    },
    {
      "sourceType": "maps_scraper",
      "leadId": "0x875f805443d4e56d:0xa2eba4eb4b7eb5ba",
      "place_id": "",
      "cid": "",
      "data_id": "0x875f805443d4e56d:0xa2eba4eb4b7eb5ba",
      "name": "SOS Roofing",
      "category": "",
      "categories": [],
      "address": "Chaucer St, Yokine WA 6060",
      "city": "perth",
      "niche": "roofer",
      "phone": "(08)62855700",
      "website": "https://www.sos-roofing.com.au/",
      "google_maps_url": "",
      "rating": 4.6,
      "review_count": 0,
      "latitude": -31.90516,
      "longitude": 115.856838,
      "timezone": "Australia/Perth",
      "price_range": "",
      "websiteStatus": "independent_https_site",
      "discoveryScore": 30,
      "relevance": {
        "relevant": true,
        "reason": "matched_category_or_name",
        "matched": [
          "roof"
        ]
      },
      "recommendedAction": "skip",
      "signals": {
        "hasPhone": true,
        "hasWebsite": true,
        "hasMenuLink": true,
        "hasReservationLink": true,
        "hasOrderOnlineLink": true,
        "imageCount": 0,
        "hasPopularTimes": true,
        "hasAboutAttributes": false
      },
      "sourceQuery": "roofer in perth"
    }
  ]
}
